./BUILD_GUIDE.md
./LICENSE
./PKG-INFO
./README.md
./UPGRADE_GUIDE.md
./ai_interface.py
./config.py
./create_release.md
./git_diff_analyzer.py
./gui_main.py
./image-1.png
./image.png
./publish.sh
./pyproject.toml
./user_notification.md
./utils.py
git_ai_commit_gui-0.2.1.dist-info/METADATA
git_ai_commit_gui-0.2.1.dist-info/WHEEL
git_ai_commit_gui-0.2.1.dist-info/entry_points.txt
git_ai_commit_gui-0.2.1.dist-info/licenses/LICENSE
git_ai_commit_gui-0.2.1.dist-info/RECORD
