Metadata-Version: 2.4
Name: git-ai-commit-gui
Version: 0.2.1
Summary: 基于AI的Git提交消息生成工具，提供智能分析和规范化的提交消息
Project-URL: Homepage, https://github.com/duolabmeng6/ai_git_commit_gui
Project-URL: Repository, https://github.com/duolabmeng6/ai_git_commit_gui
Project-URL: Issues, https://github.com/duolabmeng6/ai_git_commit_gui/issues
Project-URL: Documentation, https://github.com/duolabmeng6/ai_git_commit_gui#readme
Author-email: duolabmeng6 <1715109585@qq.com>
Maintainer-email: duolabmeng6 <1715109585@qq.com>
License: MIT
License-File: LICENSE
Keywords: ai,automation,commit,git,gui,python
Classifier: Development Status :: 4 - Beta
Classifier: Environment :: X11 Applications :: Qt
Classifier: Intended Audience :: Developers
Classifier: License :: OSI Approved :: MIT License
Classifier: Natural Language :: Chinese (Simplified)
Classifier: Operating System :: OS Independent
Classifier: Programming Language :: Python :: 3
Classifier: Programming Language :: Python :: 3.12
Classifier: Programming Language :: Python :: 3.13
Classifier: Topic :: Software Development :: Libraries :: Python Modules
Classifier: Topic :: Software Development :: Version Control :: Git
Classifier: Topic :: Utilities
Requires-Python: >=3.12
Requires-Dist: pyside6>=6.9.1
Requires-Dist: requests>=2.32.3
